shipyard_openai_dalle_e2/__init__.py
shipyard_openai_dalle_e2/cli/__init__.py
shipyard_openai_dalle_e2/cli/dalle_photos.py
shipyard_openai_dalle_e2-0.1.1a0.dist-info/METADATA
shipyard_openai_dalle_e2-0.1.1a0.dist-info/WHEEL
shipyard_openai_dalle_e2-0.1.1a0.dist-info/RECORD
