Metadata-Version: 2.1
Name: shipyard-openai-dalle-e2
Version: 0.1.1a0
Summary: 
Author: johnathan-rodriguez
Author-email: johnathan.rodriguez@shipyardapp.com
Requires-Python: >=3.9,<4.0
Classifier: Programming Language :: Python :: 3
Classifier: Programming Language :: Python :: 3.9
Classifier: Programming Language :: Python :: 3.10
Classifier: Programming Language :: Python :: 3.11
Requires-Dist: openai (>=1.6.1,<2.0.0)
Requires-Dist: requests (>=2.31.0,<3.0.0)
